substrateinterface/__init__.py
substrateinterface-1.0.0.dist-info/METADATA
substrateinterface-1.0.0.dist-info/WHEEL
substrateinterface-1.0.0.dist-info/top_level.txt
substrateinterface-1.0.0.dist-info/RECORD
